changelog/__init__.py
changelog/tests/__init__.py
changelog/tests/test_changelog.py
github_changelog-1.5.0.dist-info/LICENSE
github_changelog-1.5.0.dist-info/METADATA
github_changelog-1.5.0.dist-info/WHEEL
github_changelog-1.5.0.dist-info/entry_points.txt
github_changelog-1.5.0.dist-info/top_level.txt
github_changelog-1.5.0.dist-info/RECORD
