Metadata-Version: 2.1
Name: github-changelog
Version: 1.5.0
Summary: GitHub Pull Request changelog generator
Home-page: https://github.com/cfpb/github-changelog
Author: CFPB
License: CC0
Platform: UNKNOWN
Requires-Dist: requests (>=2.13)
Provides-Extra: testing
Requires-Dist: mock (>=2.0.0) ; extra == 'testing'
Requires-Dist: coverage (>=3.7.0) ; extra == 'testing'
Requires-Dist: flake8 (>=2.2.0) ; extra == 'testing'
